chromox/__init__.py
chromox/protein_descriptors/__init__.py
chromox/protein_descriptors/descriptors.py
chromox/protein_descriptors/table.py
chromox-0.1.0.dist-info/WHEEL
chromox-0.1.0.dist-info/METADATA
chromox-0.1.0.dist-info/RECORD
