Metadata-Version: 2.1
Name: chromox
Version: 0.1.0
Summary: 
Author: jfwu
Author-email: jfwu.ai@hotmail.com
Requires-Python: >=3.7,<4.0
Classifier: Programming Language :: Python :: 3
Classifier: Programming Language :: Python :: 3.10
Classifier: Programming Language :: Python :: 3.7
Classifier: Programming Language :: Python :: 3.8
Classifier: Programming Language :: Python :: 3.9
Requires-Dist: numpy
